{
  "project_info": {
    "project_number": "619322724525",
    "project_id": "fibasketfood",
    "storage_bucket": "fibasketfood.appspot.com"
  },
  "client": [
    {
      "client_info": {
        "mobilesdk_app_id": "1:619322724525:android:5439d4c2578a5cb83c3624",
        "android_client_info": {
          "package_name": "com.example.fibasketfood"
        }
      },
      "oauth_client": [
        {
          "client_id": "619322724525-vfeql1ptfjoimuvtv58j38t1p1butmel.apps.googleusercontent.com",
          "client_type": 3
        }
      ],
      "api_key": [
        {
          "current_key": "AIzaSyCftNUpqVO2oy63rHYP9JjZO8s2HbYRQ40"
        }
      ],
      "services": {
        "appinvite_service": {
          "other_platform_oauth_client": [
            {
              "client_id": "619322724525-vfeql1ptfjoimuvtv58j38t1p1butmel.apps.googleusercontent.com",
              "client_type": 3
            }
          ]
        }
      }
    }
  ],
  "configuration_version": "1"
}